ufish/__init__.py
ufish/__main__.py
ufish/api.py
ufish/cli.py
ufish/data.py
ufish/model/__init__.py
ufish/model/loss.py
ufish/model/train.py
ufish/model/network/__init__.py
ufish/model/network/spot_learn.py
ufish/model/network/ufish_net.py
ufish/model/weights/v1.0-alldata-ufish_c32.onnx
ufish/utils/__init__.py
ufish/utils/img.py
ufish/utils/log.py
ufish/utils/metrics.py
ufish/utils/metrics_deepblink.py
ufish/utils/ngff.py
ufish/utils/plot.py
ufish/utils/spot_calling.py
ufish-0.1.1.dist-info/LICENSE
ufish-0.1.1.dist-info/METADATA
ufish-0.1.1.dist-info/WHEEL
ufish-0.1.1.dist-info/entry_points.txt
ufish-0.1.1.dist-info/top_level.txt
ufish-0.1.1.dist-info/RECORD
