Metadata-Version: 2.1
Name: ufish
Version: 0.1.1
Summary: Deep learning based spot detection for FISH images.
Home-page: https://github.com/GangCaoLab/U-FISH
Author: Weize Xu, Huaiyuan Cai, Qian Zhang
Author-email: vet.xwz@gmail.com
License: MIT
Keywords: Spot detection,FISH,Bioimage analysis,Image processing,Deep learning,U-Net
Classifier: Development Status :: 3 - Alpha
Classifier: Operating System :: OS Independent
Classifier: Programming Language :: Python
Classifier: Programming Language :: Python :: 3
Classifier: Programming Language :: Python :: 3.9
Classifier: Programming Language :: Python :: 3.10
Classifier: Programming Language :: Python :: 3.11
Classifier: License :: OSI Approved :: MIT License
Classifier: Intended Audience :: Science/Research
Requires-Python: >=3.9, <4
License-File: LICENSE
Requires-Dist: numpy
Requires-Dist: scipy
Requires-Dist: pandas
Requires-Dist: matplotlib
Requires-Dist: torch
Requires-Dist: torchvision
Requires-Dist: scikit-image
Requires-Dist: scikit-learn
Requires-Dist: fire
Requires-Dist: loguru
Requires-Dist: tensorboard
Requires-Dist: imagecodecs
Requires-Dist: onnx
Requires-Dist: onnxruntime
Requires-Dist: zarr
Requires-Dist: ome-zarr
Provides-Extra: dev
Requires-Dist: pip ; extra == 'dev'
Requires-Dist: setuptools ; extra == 'dev'
Requires-Dist: wheel ; extra == 'dev'
Requires-Dist: twine ; extra == 'dev'
Requires-Dist: ipdb ; extra == 'dev'
Requires-Dist: pytest ; extra == 'dev'
Requires-Dist: pytest-cov ; extra == 'dev'
Requires-Dist: pytest-asyncio ; extra == 'dev'
Requires-Dist: flake8 ; extra == 'dev'
Requires-Dist: mypy ; extra == 'dev'
Requires-Dist: mkdocs ; extra == 'dev'
Requires-Dist: mkdocs-material ; extra == 'dev'
Requires-Dist: mkdocstrings[python] ; extra == 'dev'
Requires-Dist: mkdocs-autorefs ; extra == 'dev'
